{
  "generatedAt": "2026-06-21T09:16:32.346Z",
  "collections": [
    {
      "name": "users",
      "type": "auth",
      "apiRules": {
        "list": "id = @request.auth.id",
        "view": "id = @request.auth.id",
        "create": "",
        "update": "id = @request.auth.id",
        "delete": "id = @request.auth.id"
      },
      "fields": [
        {
          "name": "name",
          "type": "text",
          "required": false,
          "system": false
        },
        {
          "name": "avatar",
          "type": "file",
          "required": false,
          "system": false
        },
        {
          "name": "created",
          "type": "autodate",
          "required": false,
          "system": false,
          "autodateTriggers": [
            "onCreate"
          ]
        },
        {
          "name": "updated",
          "type": "autodate",
          "required": false,
          "system": false,
          "autodateTriggers": [
            "onCreate",
            "onUpdate"
          ]
        },
        {
          "name": "preferencias_ui",
          "type": "json",
          "required": false,
          "system": false
        }
      ],
      "indexes": [
        "CREATE UNIQUE INDEX `idx_tokenKey__pb_users_auth_` ON `users` (`tokenKey`)",
        "CREATE UNIQUE INDEX `idx_email__pb_users_auth_` ON `users` (`email`) WHERE `email` != ''"
      ]
    },
    {
      "name": "categorias",
      "type": "base",
      "apiRules": {
        "list": "@request.auth.id != ''",
        "view": "@request.auth.id != ''",
        "create": "@request.auth.id != ''",
        "update": "@request.auth.id != ''",
        "delete": "@request.auth.id != ''"
      },
      "fields": [
        {
          "name": "nome_pt",
          "type": "text",
          "required": true,
          "system": false
        },
        {
          "name": "nome_en",
          "type": "text",
          "required": false,
          "system": false
        },
        {
          "name": "created",
          "type": "autodate",
          "required": false,
          "system": false,
          "autodateTriggers": [
            "onCreate"
          ]
        },
        {
          "name": "updated",
          "type": "autodate",
          "required": false,
          "system": false,
          "autodateTriggers": [
            "onCreate",
            "onUpdate"
          ]
        },
        {
          "name": "color",
          "type": "text",
          "required": false,
          "system": false
        }
      ],
      "indexes": []
    },
    {
      "name": "linhas",
      "type": "base",
      "apiRules": {
        "list": "@request.auth.id != ''",
        "view": "@request.auth.id != ''",
        "create": "@request.auth.id != ''",
        "update": "@request.auth.id != ''",
        "delete": "@request.auth.id != ''"
      },
      "fields": [
        {
          "name": "categoria_id",
          "type": "relation",
          "required": true,
          "system": false,
          "collectionRef": "categorias"
        },
        {
          "name": "nome_pt",
          "type": "text",
          "required": true,
          "system": false
        },
        {
          "name": "nome_en",
          "type": "text",
          "required": false,
          "system": false
        },
        {
          "name": "created",
          "type": "autodate",
          "required": false,
          "system": false,
          "autodateTriggers": [
            "onCreate"
          ]
        },
        {
          "name": "updated",
          "type": "autodate",
          "required": false,
          "system": false,
          "autodateTriggers": [
            "onCreate",
            "onUpdate"
          ]
        },
        {
          "name": "color",
          "type": "text",
          "required": false,
          "system": false
        }
      ],
      "indexes": [
        "CREATE INDEX idx_linhas_categoria_id ON linhas (categoria_id)"
      ]
    },
    {
      "name": "acabamentos",
      "type": "base",
      "apiRules": {
        "list": "@request.auth.id != ''",
        "view": "@request.auth.id != ''",
        "create": "@request.auth.id != ''",
        "update": "@request.auth.id != ''",
        "delete": "@request.auth.id != ''"
      },
      "fields": [
        {
          "name": "codigo",
          "type": "text",
          "required": true,
          "system": false
        },
        {
          "name": "nome_pt",
          "type": "text",
          "required": true,
          "system": false
        },
        {
          "name": "nome_en",
          "type": "text",
          "required": false,
          "system": false
        },
        {
          "name": "created",
          "type": "autodate",
          "required": false,
          "system": false,
          "autodateTriggers": [
            "onCreate"
          ]
        },
        {
          "name": "updated",
          "type": "autodate",
          "required": false,
          "system": false,
          "autodateTriggers": [
            "onCreate",
            "onUpdate"
          ]
        },
        {
          "name": "cor_hex",
          "type": "text",
          "required": false,
          "system": false
        }
      ],
      "indexes": [
        "CREATE UNIQUE INDEX idx_acabamentos_codigo ON acabamentos (codigo)"
      ]
    },
    {
      "name": "ncm",
      "type": "base",
      "apiRules": {
        "list": "@request.auth.id != ''",
        "view": "@request.auth.id != ''",
        "create": "@request.auth.id != ''",
        "update": "@request.auth.id != ''",
        "delete": "@request.auth.id != ''"
      },
      "fields": [
        {
          "name": "codigo",
          "type": "text",
          "required": true,
          "system": false
        },
        {
          "name": "ii",
          "type": "number",
          "required": false,
          "system": false
        },
        {
          "name": "ipi",
          "type": "number",
          "required": false,
          "system": false
        },
        {
          "name": "pis",
          "type": "number",
          "required": false,
          "system": false
        },
        {
          "name": "cofins",
          "type": "number",
          "required": false,
          "system": false
        },
        {
          "name": "created",
          "type": "autodate",
          "required": false,
          "system": false,
          "autodateTriggers": [
            "onCreate"
          ]
        },
        {
          "name": "updated",
          "type": "autodate",
          "required": false,
          "system": false,
          "autodateTriggers": [
            "onCreate",
            "onUpdate"
          ]
        },
        {
          "name": "observacoes",
          "type": "text",
          "required": false,
          "system": false
        }
      ],
      "indexes": [
        "CREATE UNIQUE INDEX idx_ncm_codigo ON ncm (codigo)"
      ]
    },
    {
      "name": "itens",
      "type": "base",
      "apiRules": {
        "list": "@request.auth.id != ''",
        "view": "@request.auth.id != ''",
        "create": "@request.auth.id != ''",
        "update": "@request.auth.id != ''",
        "delete": "@request.auth.id != ''"
      },
      "fields": [
        {
          "name": "sku",
          "type": "text",
          "required": true,
          "system": false
        },
        {
          "name": "linha_id",
          "type": "relation",
          "required": true,
          "system": false,
          "collectionRef": "linhas"
        },
        {
          "name": "descr_pt",
          "type": "text",
          "required": false,
          "system": false
        },
        {
          "name": "descr_en",
          "type": "text",
          "required": false,
          "system": false
        },
        {
          "name": "tamanho",
          "type": "text",
          "required": false,
          "system": false
        },
        {
          "name": "acabamento_id",
          "type": "relation",
          "required": false,
          "system": false,
          "collectionRef": "acabamentos"
        },
        {
          "name": "ncm_id",
          "type": "relation",
          "required": false,
          "system": false,
          "collectionRef": "ncm"
        },
        {
          "name": "preco_compra",
          "type": "number",
          "required": false,
          "system": false
        },
        {
          "name": "preco_venda",
          "type": "number",
          "required": false,
          "system": false
        },
        {
          "name": "item_id_books",
          "type": "text",
          "required": false,
          "system": false
        },
        {
          "name": "foto_url",
          "type": "url",
          "required": false,
          "system": false
        },
        {
          "name": "ativo",
          "type": "bool",
          "required": false,
          "system": false
        },
        {
          "name": "sincronizado_com_zoho",
          "type": "bool",
          "required": false,
          "system": false
        },
        {
          "name": "data_sincronizacao",
          "type": "date",
          "required": false,
          "system": false
        },
        {
          "name": "created",
          "type": "autodate",
          "required": false,
          "system": false,
          "autodateTriggers": [
            "onCreate"
          ]
        },
        {
          "name": "updated",
          "type": "autodate",
          "required": false,
          "system": false,
          "autodateTriggers": [
            "onCreate",
            "onUpdate"
          ]
        },
        {
          "name": "norma",
          "type": "text",
          "required": false,
          "system": false
        },
        {
          "name": "descricao_base_pt",
          "type": "text",
          "required": false,
          "system": false
        },
        {
          "name": "descricao_base_en",
          "type": "text",
          "required": false,
          "system": false
        },
        {
          "name": "tipo_rosca",
          "type": "text",
          "required": false,
          "system": false
        },
        {
          "name": "comprimento_rosca",
          "type": "text",
          "required": false,
          "system": false
        },
        {
          "name": "informacao_extra",
          "type": "text",
          "required": false,
          "system": false
        },
        {
          "name": "descricao_extra",
          "type": "text",
          "required": false,
          "system": false
        },
        {
          "name": "fornecedor_ultima_atualizacao",
          "type": "text",
          "required": false,
          "system": false
        },
        {
          "name": "descricao_base_id",
          "type": "relation",
          "required": false,
          "system": false,
          "collectionRef": "descricoes_base"
        },
        {
          "name": "unidade_id",
          "type": "relation",
          "required": false,
          "system": false,
          "collectionRef": "unidades_medida"
        },
        {
          "name": "ii",
          "type": "number",
          "required": false,
          "system": false
        },
        {
          "name": "ipi",
          "type": "number",
          "required": false,
          "system": false
        },
        {
          "name": "pis",
          "type": "number",
          "required": false,
          "system": false
        },
        {
          "name": "cofins",
          "type": "number",
          "required": false,
          "system": false
        },
        {
          "name": "comprimento_rosca_en",
          "type": "text",
          "required": false,
          "system": false
        },
        {
          "name": "data_atualizacao",
          "type": "date",
          "required": false,
          "system": false
        },
        {
          "name": "validade_preco",
          "type": "date",
          "required": false,
          "system": false
        },
        {
          "name": "descricao_catalogo_pt",
          "type": "text",
          "required": false,
          "system": false
        },
        {
          "name": "descricao_catalogo_en",
          "type": "text",
          "required": false,
          "system": false
        },
        {
          "name": "descricao_curta",
          "type": "text",
          "required": false,
          "system": false
        },
        {
          "name": "descricao_curta_en",
          "type": "text",
          "required": false,
          "system": false
        },
        {
          "name": "informacao_extra_en",
          "type": "text",
          "required": false,
          "system": false
        },
        {
          "name": "descricao_extra_en",
          "type": "text",
          "required": false,
          "system": false
        },
        {
          "name": "grau",
          "type": "text",
          "required": false,
          "system": false
        },
        {
          "name": "unidade",
          "type": "text",
          "required": false,
          "system": false
        }
      ],
      "indexes": [
        "CREATE UNIQUE INDEX idx_itens_sku ON itens (sku)",
        "CREATE INDEX idx_itens_linha_id ON itens (linha_id)",
        "CREATE INDEX idx_itens_acabamento_id ON itens (acabamento_id)",
        "CREATE INDEX idx_itens_ncm_id ON itens (ncm_id)",
        "CREATE INDEX `idx_itens_descricao_curta` ON `itens` (descricao_curta)",
        "CREATE INDEX `idx_itens_tamanho` ON `itens` (tamanho)"
      ]
    },
    {
      "name": "logs_importacao",
      "type": "base",
      "apiRules": {
        "list": "@request.auth.id != ''",
        "view": "@request.auth.id != ''",
        "create": "@request.auth.id != ''",
        "update": "@request.auth.id != ''",
        "delete": "@request.auth.id != ''"
      },
      "fields": [
        {
          "name": "arquivo_nome",
          "type": "text",
          "required": true,
          "system": false
        },
        {
          "name": "total_processado",
          "type": "number",
          "required": false,
          "system": false
        },
        {
          "name": "sucessos",
          "type": "number",
          "required": false,
          "system": false
        },
        {
          "name": "duplicados",
          "type": "number",
          "required": false,
          "system": false
        },
        {
          "name": "erros",
          "type": "number",
          "required": false,
          "system": false
        },
        {
          "name": "detalhes_erros",
          "type": "json",
          "required": false,
          "system": false
        },
        {
          "name": "created",
          "type": "autodate",
          "required": false,
          "system": false,
          "autodateTriggers": [
            "onCreate"
          ]
        },
        {
          "name": "updated",
          "type": "autodate",
          "required": false,
          "system": false,
          "autodateTriggers": [
            "onCreate",
            "onUpdate"
          ]
        }
      ],
      "indexes": []
    },
    {
      "name": "potenciais",
      "type": "base",
      "apiRules": {
        "list": "@request.auth.id != ''",
        "view": "@request.auth.id != ''",
        "create": "@request.auth.id != ''",
        "update": "@request.auth.id != ''",
        "delete": "@request.auth.id != ''"
      },
      "fields": [
        {
          "name": "numero_potencial",
          "type": "text",
          "required": true,
          "system": false
        },
        {
          "name": "cliente",
          "type": "text",
          "required": true,
          "system": false
        },
        {
          "name": "status",
          "type": "text",
          "required": true,
          "system": false
        },
        {
          "name": "created",
          "type": "autodate",
          "required": false,
          "system": false,
          "autodateTriggers": [
            "onCreate"
          ]
        },
        {
          "name": "updated",
          "type": "autodate",
          "required": false,
          "system": false,
          "autodateTriggers": [
            "onCreate",
            "onUpdate"
          ]
        },
        {
          "name": "observacoes",
          "type": "text",
          "required": false,
          "system": false
        },
        {
          "name": "nome_potencial",
          "type": "text",
          "required": false,
          "system": false
        },
        {
          "name": "proprietario",
          "type": "text",
          "required": false,
          "system": false
        },
        {
          "name": "nome_comprador",
          "type": "text",
          "required": false,
          "system": false
        },
        {
          "name": "notas",
          "type": "text",
          "required": false,
          "system": false
        },
        {
          "name": "anexos",
          "type": "file",
          "required": false,
          "system": false
        },
        {
          "name": "estagio_id",
          "type": "relation",
          "required": false,
          "system": false,
          "collectionRef": "estagios_potencial"
        }
      ],
      "indexes": [
        "CREATE UNIQUE INDEX idx_potenciais_numero ON potenciais (numero_potencial)",
        "CREATE INDEX `idx_potenciais_nome` ON `potenciais` (nome_potencial)",
        "CREATE INDEX `idx_potenciais_proprietario` ON `potenciais` (proprietario)",
        "CREATE INDEX `idx_potenciais_estagio_id` ON `potenciais` (estagio_id)"
      ]
    },
    {
      "name": "potencial_itens",
      "type": "base",
      "apiRules": {
        "list": "@request.auth.id != ''",
        "view": "@request.auth.id != ''",
        "create": "@request.auth.id != ''",
        "update": "@request.auth.id != ''",
        "delete": "@request.auth.id != ''"
      },
      "fields": [
        {
          "name": "potencial_id",
          "type": "relation",
          "required": true,
          "system": false,
          "collectionRef": "potenciais"
        },
        {
          "name": "item_id",
          "type": "relation",
          "required": true,
          "system": false,
          "collectionRef": "itens"
        },
        {
          "name": "quantidade",
          "type": "number",
          "required": true,
          "system": false
        },
        {
          "name": "preco_unitario",
          "type": "number",
          "required": false,
          "system": false
        },
        {
          "name": "observacoes",
          "type": "text",
          "required": false,
          "system": false
        },
        {
          "name": "created",
          "type": "autodate",
          "required": false,
          "system": false,
          "autodateTriggers": [
            "onCreate"
          ]
        },
        {
          "name": "updated",
          "type": "autodate",
          "required": false,
          "system": false,
          "autodateTriggers": [
            "onCreate",
            "onUpdate"
          ]
        },
        {
          "name": "unidade_medida",
          "type": "text",
          "required": false,
          "system": false
        },
        {
          "name": "ordem",
          "type": "number",
          "required": false,
          "system": false
        }
      ],
      "indexes": []
    },
    {
      "name": "atributos_linha",
      "type": "base",
      "apiRules": {
        "list": "@request.auth.id != ''",
        "view": "@request.auth.id != ''",
        "create": "@request.auth.id != ''",
        "update": "@request.auth.id != ''",
        "delete": "@request.auth.id != ''"
      },
      "fields": [
        {
          "name": "linha_id",
          "type": "relation",
          "required": true,
          "system": false,
          "collectionRef": "linhas"
        },
        {
          "name": "tipo_atributo",
          "type": "text",
          "required": false,
          "system": false
        },
        {
          "name": "nome_campo_customizado",
          "type": "text",
          "required": false,
          "system": false
        },
        {
          "name": "created",
          "type": "autodate",
          "required": false,
          "system": false,
          "autodateTriggers": [
            "onCreate"
          ]
        },
        {
          "name": "updated",
          "type": "autodate",
          "required": false,
          "system": false,
          "autodateTriggers": [
            "onCreate",
            "onUpdate"
          ]
        },
        {
          "name": "campo_sistema",
          "type": "text",
          "required": true,
          "system": false
        },
        {
          "name": "nome_customizado",
          "type": "text",
          "required": false,
          "system": false
        },
        {
          "name": "ativo",
          "type": "bool",
          "required": false,
          "system": false
        }
      ],
      "indexes": []
    },
    {
      "name": "foto_catalogo",
      "type": "base",
      "apiRules": {
        "list": "@request.auth.id != ''",
        "view": "@request.auth.id != ''",
        "create": "@request.auth.id != ''",
        "update": "@request.auth.id != ''",
        "delete": "@request.auth.id != ''"
      },
      "fields": [
        {
          "name": "tipo",
          "type": "text",
          "required": false,
          "system": false
        },
        {
          "name": "subtipo",
          "type": "text",
          "required": false,
          "system": false
        },
        {
          "name": "tamanho",
          "type": "text",
          "required": false,
          "system": false
        },
        {
          "name": "acabamento_id",
          "type": "relation",
          "required": false,
          "system": false,
          "collectionRef": "acabamentos"
        },
        {
          "name": "url_foto",
          "type": "url",
          "required": false,
          "system": false
        },
        {
          "name": "created",
          "type": "autodate",
          "required": false,
          "system": false,
          "autodateTriggers": [
            "onCreate"
          ]
        },
        {
          "name": "updated",
          "type": "autodate",
          "required": false,
          "system": false,
          "autodateTriggers": [
            "onCreate",
            "onUpdate"
          ]
        },
        {
          "name": "descricao",
          "type": "text",
          "required": false,
          "system": false
        },
        {
          "name": "arquivo",
          "type": "file",
          "required": false,
          "system": false
        }
      ],
      "indexes": [
        "CREATE INDEX idx_foto_catalogo_lookup ON foto_catalogo (tipo, subtipo, tamanho, acabamento_id)"
      ]
    },
    {
      "name": "unidades_medida",
      "type": "base",
      "apiRules": {
        "list": "@request.auth.id != ''",
        "view": "@request.auth.id != ''",
        "create": "@request.auth.id != ''",
        "update": "@request.auth.id != ''",
        "delete": "@request.auth.id != ''"
      },
      "fields": [
        {
          "name": "nome",
          "type": "text",
          "required": true,
          "system": false
        },
        {
          "name": "created",
          "type": "autodate",
          "required": false,
          "system": false,
          "autodateTriggers": [
            "onCreate"
          ]
        },
        {
          "name": "updated",
          "type": "autodate",
          "required": false,
          "system": false,
          "autodateTriggers": [
            "onCreate",
            "onUpdate"
          ]
        }
      ],
      "indexes": [
        "CREATE UNIQUE INDEX idx_unidades_medida_nome ON unidades_medida (nome)"
      ]
    },
    {
      "name": "descricoes_base",
      "type": "base",
      "apiRules": {
        "list": "@request.auth.id != ''",
        "view": "@request.auth.id != ''",
        "create": "@request.auth.id != ''",
        "update": "@request.auth.id != ''",
        "delete": "@request.auth.id != ''"
      },
      "fields": [
        {
          "name": "codigo",
          "type": "text",
          "required": true,
          "system": false
        },
        {
          "name": "nome_pt",
          "type": "text",
          "required": true,
          "system": false
        },
        {
          "name": "nome_en",
          "type": "text",
          "required": false,
          "system": false
        },
        {
          "name": "categoria_id",
          "type": "relation",
          "required": true,
          "system": false,
          "collectionRef": "categorias"
        },
        {
          "name": "linha_id",
          "type": "relation",
          "required": true,
          "system": false,
          "collectionRef": "linhas"
        },
        {
          "name": "ncm_id",
          "type": "relation",
          "required": false,
          "system": false,
          "collectionRef": "ncm"
        },
        {
          "name": "ativo",
          "type": "bool",
          "required": false,
          "system": false
        },
        {
          "name": "created",
          "type": "autodate",
          "required": false,
          "system": false,
          "autodateTriggers": [
            "onCreate"
          ]
        },
        {
          "name": "updated",
          "type": "autodate",
          "required": false,
          "system": false,
          "autodateTriggers": [
            "onCreate",
            "onUpdate"
          ]
        }
      ],
      "indexes": [
        "CREATE UNIQUE INDEX idx_descricoes_base_codigo ON descricoes_base (codigo)",
        "CREATE UNIQUE INDEX `idx_descricoes_base_nome_pt` ON `descricoes_base` (nome_pt)"
      ]
    },
    {
      "name": "ncm_audit_logs",
      "type": "base",
      "apiRules": {
        "list": "@request.auth.id != ''",
        "view": "@request.auth.id != ''",
        "create": null,
        "update": null,
        "delete": null
      },
      "fields": [
        {
          "name": "ncm_id",
          "type": "relation",
          "required": true,
          "system": false,
          "collectionRef": "ncm"
        },
        {
          "name": "user_id",
          "type": "relation",
          "required": false,
          "system": false,
          "collectionRef": "users"
        },
        {
          "name": "action",
          "type": "text",
          "required": true,
          "system": false
        },
        {
          "name": "previous_values",
          "type": "json",
          "required": false,
          "system": false
        },
        {
          "name": "new_values",
          "type": "json",
          "required": false,
          "system": false
        },
        {
          "name": "created",
          "type": "autodate",
          "required": false,
          "system": false,
          "autodateTriggers": [
            "onCreate"
          ]
        },
        {
          "name": "updated",
          "type": "autodate",
          "required": false,
          "system": false,
          "autodateTriggers": [
            "onCreate",
            "onUpdate"
          ]
        }
      ],
      "indexes": [
        "CREATE INDEX idx_ncm_audit_ncm_id ON ncm_audit_logs (ncm_id)",
        "CREATE INDEX idx_ncm_audit_created ON ncm_audit_logs (created)"
      ]
    },
    {
      "name": "historico_precos",
      "type": "base",
      "apiRules": {
        "list": "@request.auth.id != ''",
        "view": "@request.auth.id != ''",
        "create": "@request.auth.id != ''",
        "update": "@request.auth.id != ''",
        "delete": "@request.auth.id != ''"
      },
      "fields": [
        {
          "name": "item_id",
          "type": "relation",
          "required": true,
          "system": false,
          "collectionRef": "itens"
        },
        {
          "name": "preco",
          "type": "number",
          "required": false,
          "system": false
        },
        {
          "name": "fornecedor",
          "type": "text",
          "required": false,
          "system": false
        },
        {
          "name": "data_cotacao",
          "type": "date",
          "required": false,
          "system": false
        },
        {
          "name": "created",
          "type": "autodate",
          "required": false,
          "system": false,
          "autodateTriggers": [
            "onCreate"
          ]
        },
        {
          "name": "updated",
          "type": "autodate",
          "required": false,
          "system": false,
          "autodateTriggers": [
            "onCreate",
            "onUpdate"
          ]
        }
      ],
      "indexes": [
        "CREATE INDEX idx_historico_precos_item_id ON historico_precos (item_id)",
        "CREATE INDEX idx_historico_precos_data ON historico_precos (data_cotacao DESC)"
      ]
    },
    {
      "name": "potencial_notas",
      "type": "base",
      "apiRules": {
        "list": "@request.auth.id != ''",
        "view": "@request.auth.id != ''",
        "create": "@request.auth.id != ''",
        "update": "@request.auth.id != '' && user_id = @request.auth.id",
        "delete": "@request.auth.id != '' && user_id = @request.auth.id"
      },
      "fields": [
        {
          "name": "potencial_id",
          "type": "relation",
          "required": true,
          "system": false,
          "collectionRef": "potenciais"
        },
        {
          "name": "user_id",
          "type": "relation",
          "required": true,
          "system": false,
          "collectionRef": "users"
        },
        {
          "name": "conteudo",
          "type": "text",
          "required": true,
          "system": false
        },
        {
          "name": "created",
          "type": "autodate",
          "required": false,
          "system": false,
          "autodateTriggers": [
            "onCreate"
          ]
        },
        {
          "name": "updated",
          "type": "autodate",
          "required": false,
          "system": false,
          "autodateTriggers": [
            "onCreate",
            "onUpdate"
          ]
        }
      ],
      "indexes": []
    },
    {
      "name": "status_potencial",
      "type": "base",
      "apiRules": {
        "list": "@request.auth.id != ''",
        "view": "@request.auth.id != ''",
        "create": "@request.auth.id != ''",
        "update": "@request.auth.id != ''",
        "delete": "@request.auth.id != ''"
      },
      "fields": [
        {
          "name": "nome",
          "type": "text",
          "required": true,
          "system": false
        },
        {
          "name": "cor_hex",
          "type": "text",
          "required": true,
          "system": false
        },
        {
          "name": "created",
          "type": "autodate",
          "required": false,
          "system": false,
          "autodateTriggers": [
            "onCreate"
          ]
        },
        {
          "name": "updated",
          "type": "autodate",
          "required": false,
          "system": false,
          "autodateTriggers": [
            "onCreate",
            "onUpdate"
          ]
        }
      ],
      "indexes": []
    },
    {
      "name": "estagios_potencial",
      "type": "base",
      "apiRules": {
        "list": "@request.auth.id != ''",
        "view": "@request.auth.id != ''",
        "create": "@request.auth.id != ''",
        "update": "@request.auth.id != ''",
        "delete": "@request.auth.id != ''"
      },
      "fields": [
        {
          "name": "nome",
          "type": "text",
          "required": true,
          "system": false
        },
        {
          "name": "cor_hex",
          "type": "text",
          "required": false,
          "system": false
        },
        {
          "name": "ordem",
          "type": "number",
          "required": false,
          "system": false
        },
        {
          "name": "created",
          "type": "autodate",
          "required": false,
          "system": false,
          "autodateTriggers": [
            "onCreate"
          ]
        },
        {
          "name": "updated",
          "type": "autodate",
          "required": false,
          "system": false,
          "autodateTriggers": [
            "onCreate",
            "onUpdate"
          ]
        }
      ],
      "indexes": []
    }
  ]
}